ckanext_googleanalytics-2.5.1-py3.12-nspkg.pth
ckanext/googleanalytics/__init__.py
ckanext/googleanalytics/cli.py
ckanext/googleanalytics/commands.py
ckanext/googleanalytics/config.py
ckanext/googleanalytics/config_declaration.yaml
ckanext/googleanalytics/controller.py
ckanext/googleanalytics/dbutil.py
ckanext/googleanalytics/ga_auth.py
ckanext/googleanalytics/helpers.py
ckanext/googleanalytics/interfaces.py
ckanext/googleanalytics/utils.py
ckanext/googleanalytics/views.py
ckanext/googleanalytics/assets/googleanalytics_event_tracking.js
ckanext/googleanalytics/assets/webassets.yml
ckanext/googleanalytics/logic/__init__.py
ckanext/googleanalytics/logic/action.py
ckanext/googleanalytics/logic/auth.py
ckanext/googleanalytics/logic/schema.py
ckanext/googleanalytics/model/__init__.py
ckanext/googleanalytics/model/base.py
ckanext/googleanalytics/plugin/__init__.py
ckanext/googleanalytics/plugin/flask_plugin.py
ckanext/googleanalytics/plugin/pylons_plugin.py
ckanext/googleanalytics/templates/base.html
ckanext/googleanalytics/templates/page.html
ckanext/googleanalytics/templates/googleanalytics/snippets/_ga.html
ckanext/googleanalytics/templates/googleanalytics/snippets/_gtag.html
ckanext/googleanalytics/templates/googleanalytics/snippets/_gtm.html
ckanext/googleanalytics/templates/googleanalytics/snippets/event_tracking_asset.html
ckanext/googleanalytics/templates/googleanalytics/snippets/event_tracking_resource.html
ckanext/googleanalytics/templates/googleanalytics/snippets/googleanalytics_header.html
ckanext/googleanalytics/tests/__init__.py
ckanext/googleanalytics/tests/conftest.py
ckanext/googleanalytics/tests/test_config.py
ckanext/googleanalytics/tests/test_plugin.py
ckanext/googleanalytics/tests/test_view.py
ckanext/googleanalytics/tests/logic/__init__.py
ckanext/googleanalytics/tests/logic/test_action.py
ckanext_googleanalytics-2.5.1.dist-info/licenses/LICENSE.txt
ckanext_googleanalytics-2.5.1.dist-info/METADATA
ckanext_googleanalytics-2.5.1.dist-info/WHEEL
ckanext_googleanalytics-2.5.1.dist-info/entry_points.txt
ckanext_googleanalytics-2.5.1.dist-info/namespace_packages.txt
ckanext_googleanalytics-2.5.1.dist-info/top_level.txt
ckanext_googleanalytics-2.5.1.dist-info/RECORD
