Metadata-Version: 2.4
Name: ckanext-googleanalytics
Version: 2.5.1
Summary: Add GA tracking and reporting to CKAN instance
Home-page: https://github.com/ckan/ckanext-googleanalytics
Author: Seb Bacon
Author-email: seb.bacon@gmail.com
License: AGPL
Keywords: CKAN
Classifier: Development Status :: 4 - Beta
Classifier: License :: OSI Approved :: GNU Affero General Public License v3 or later (AGPLv3+)
Classifier: Programming Language :: Python :: 3.7
Classifier: Programming Language :: Python :: 3.8
Classifier: Programming Language :: Python :: 3.9
Classifier: Programming Language :: Python :: 3.10
Classifier: Programming Language :: Python :: 3.11
Classifier: Programming Language :: Python :: 3.12
Requires-Python: >=3.7
License-File: LICENSE.txt
Requires-Dist: ckantoolkit
Requires-Dist: google-api-python-client
Provides-Extra: requirements
Requires-Dist: gdata>=2.0.0; extra == "requirements"
Requires-Dist: google-api-python-client<1.7.0,>=1.6.1; extra == "requirements"
Requires-Dist: pyOpenSSL>=16.2.0; extra == "requirements"
Requires-Dist: rsa>=4.7; extra == "requirements"
Dynamic: license-file
